[
  {
    "value": "88",
    "label": "88"
  },
  {
    "value": "98",
    "label": "98"
  },
  {
    "value": "Custom Cruiser",
    "label": "Custom Cruiser"
  },
  {
    "value": "Cutlass",
    "label": "Cutlass"
  },
  {
    "value": "Cutlass Ciera",
    "label": "Cutlass Ciera"
  },
  {
    "value": "Cutlass Cruiser",
    "label": "Cutlass Cruiser"
  },
  {
    "value": "Cutlass Supreme",
    "label": "Cutlass Supreme"
  },
  {
    "value": "Intrigue",
    "label": "Intrigue"
  },
  {
    "value": "LSS",
    "label": "LSS"
  },
  {
    "value": "Regency",
    "label": "Regency"
  },
  {
    "value": "Silhouette",
    "label": "Silhouette"
  },
  {
    "value": "Toronado",
    "label": "Toronado"
  },
  {
    "value": "Achieva",
    "label": "Achieva"
  },
  {
    "value": "Alero",
    "label": "Alero"
  },
  {
    "value": "Aurora",
    "label": "Aurora"
  },
  {
    "value": "Bravada",
    "label": "Bravada"
  },
  {
    "value": "Ciera",
    "label": "Ciera"
  }
]